nixmcp/__init__.py
nixmcp/__main__.py
nixmcp/logging.py
nixmcp/server.py
nixmcp/cache/__init__.py
nixmcp/cache/html_cache.py
nixmcp/cache/simple_cache.py
nixmcp/clients/__init__.py
nixmcp/clients/elasticsearch_client.py
nixmcp/clients/home_manager_client.py
nixmcp/clients/html_client.py
nixmcp/clients/darwin/__init__.py
nixmcp/clients/darwin/darwin_client.py
nixmcp/completions/__init__.py
nixmcp/completions/home_manager.py
nixmcp/completions/nixos.py
nixmcp/completions/utils.py
nixmcp/contexts/__init__.py
nixmcp/contexts/home_manager_context.py
nixmcp/contexts/nixos_context.py
nixmcp/contexts/darwin/__init__.py
nixmcp/contexts/darwin/darwin_context.py
nixmcp/resources/__init__.py
nixmcp/resources/home_manager_resources.py
nixmcp/resources/nixos_resources.py
nixmcp/resources/darwin/__init__.py
nixmcp/resources/darwin/darwin_resources.py
nixmcp/tools/__init__.py
nixmcp/tools/home_manager_tools.py
nixmcp/tools/nixos_tools.py
nixmcp/tools/darwin/__init__.py
nixmcp/tools/darwin/darwin_tools.py
nixmcp/utils/__init__.py
nixmcp/utils/cache_helpers.py
nixmcp/utils/helpers.py
nixmcp-0.1.4.dist-info/METADATA
nixmcp-0.1.4.dist-info/WHEEL
nixmcp-0.1.4.dist-info/entry_points.txt
nixmcp-0.1.4.dist-info/licenses/LICENSE
nixmcp-0.1.4.dist-info/RECORD
