Metadata-Version: 2.4
Name: nixmcp
Version: 0.1.4
Summary: Model Context Protocol server for NixOS, Home Manager, and nix-darwin resources
Author-email: James Brink <james@utensils.io>
License-File: LICENSE
Classifier: Development Status :: 3 - Alpha
Classifier: Intended Audience :: Developers
Classifier: License :: OSI Approved :: MIT License
Classifier: Programming Language :: Python :: 3
Classifier: Programming Language :: Python :: 3.11
Requires-Python: >=3.11
Requires-Dist: beautifulsoup4>=4.13.3
Requires-Dist: mcp>=1.5.0
Requires-Dist: python-dotenv>=1.1.0
Requires-Dist: requests>=2.32.3
Provides-Extra: dev
Requires-Dist: black>=25.1.0; extra == 'dev'
Requires-Dist: flake8>=7.1.2; extra == 'dev'
Requires-Dist: pytest-asyncio>=0.26.0; extra == 'dev'
Requires-Dist: pytest-cov>=6.0.0; extra == 'dev'
Requires-Dist: pytest>=8.3.5; extra == 'dev'
